pchaa/__init__.py
pchaa/__main__.py
pchaa/about.py
pchaa-1.0.2.dist-info/LICENSE
pchaa-1.0.2.dist-info/METADATA
pchaa-1.0.2.dist-info/WHEEL
pchaa-1.0.2.dist-info/entry_points.txt
pchaa-1.0.2.dist-info/top_level.txt
pchaa-1.0.2.dist-info/RECORD
