Metadata-Version: 2.1
Name: pchaa
Version: 1.0.2
Summary: pchaa
Home-page: https://github.com/rushic24/pchaa
Author: Rushi Chaudhari
Author-email: rushic24@gmail.com
License: UNKNOWN
Keywords: python,pchaa,power,terminal
Platform: UNKNOWN
Classifier: Development Status :: 3 - Alpha
Classifier: Intended Audience :: Education
Classifier: Programming Language :: Python :: 3
License-File: LICENSE
Requires-Dist: python-libxdo
Requires-Dist: prompt-toolkit
